engi1020/__init__.py
engi1020/plotting.py
engi1020/arduino/__init__.py
engi1020/arduino/api.py
engi1020/arduino/cli.py
engi1020/arduino/dht11.py
engi1020/arduino/heart_rate.py
engi1020/arduino/io.py
engi1020/arduino/joystick.py
engi1020/arduino/oled.py
engi1020/arduino/pressure.py
engi1020/arduino/rgb_lcd.py
engi1020/arduino/rgb_led.py
engi1020/arduino/serial.py
engi1020/arduino/servo.py
engi1020/arduino/shell.py
engi1020/arduino/testing.py
engi1020/arduino/three_axis_accel.py
engi1020/arduino/tlv.py
engi1020/arduino/tracing.py
engi1020/arduino/ultra_distance.py
engi1020-5.1.4.dist-info/METADATA
engi1020-5.1.4.dist-info/WHEEL
engi1020-5.1.4.dist-info/entry_points.txt
engi1020-5.1.4.dist-info/top_level.txt
engi1020-5.1.4.dist-info/RECORD
