Metadata-Version: 2.1
Name: engi1020
Version: 5.1.4
Summary: Software library for Engineering 1020: Introduction to Programming at Memorial University.
Author: Jonathan Anderson, Lori Hogan
License: MIT
Classifier: Programming Language :: Python
Classifier: Programming Language :: Python :: 3.6
Classifier: Programming Language :: Python :: 3.7
Classifier: Programming Language :: Python :: 3.8
Classifier: Programming Language :: Python :: 3.9
Classifier: Programming Language :: Python :: 3.10
Requires-Dist: click
Requires-Dist: hexdump
Requires-Dist: matplotlib
Requires-Dist: pyserial
Requires-Dist: python-dotenv
